tboard-0.1.2.dist-info/METADATA
tboard-0.1.2.dist-info/WHEEL
tboard/__init__.py
tboard/tboard.cpython-310-x86_64-linux-gnu.so
tboard-0.1.2.dist-info/RECORD
