Metadata-Version: 2.1
Name: tboard
Version: 0.1.2
Classifier: Programming Language :: Rust
Classifier: Programming Language :: Python :: Implementation :: CPython
Classifier: Programming Language :: Python :: Implementation :: PyPy
Summary: Write and read tensorboard files.
Keywords: tensorboard,pytorch,deep-learning
License: MIT/Apache-2.0
Requires-Python: >=3.8
Project-URL: Source Code, https://github.com/LaurentMazare/tboard-rs
